{
    "path": [
        "Acknowledged Pawn",
        "Properties",
        "Inventory",
        "Properties",
        "ActiveWeapon",
        "Components",
        "ArrowComponent muzzleADSZoom"
    ],
    "state": {
        "hand": 1,
        "location_offset": {
            "x": 0.0,
            "y": -8.6899995803833,
            "z": 0.0
        },
        "permanent": true,
        "rotation_offset": {
            "w": 0.9999968409538269,
            "x": -0.002499997615814209,
            "y": 0.0,
            "z": 0.0
        }
    },
    "type": "motion_controller"
}