{
  "ID": "4be37cad-5a37-423c-95e7-349bbbbab92a",
  "exeName": "DeliverUsMars",
  "gameName": "Deliver Us Mars",
  "authorName": "Michael Cawood",
  "modifiedDate": "2024-01-13T22:00:00Z",
  "createdDate": "2024-01-13T22:00:00Z",
  "sourceName": "uevr-profiles.com",
  "sourceUrl": "https://uevr-profiles.com/game/4be37cad-5a37-423c-95e7-349bbbbab92a",
  "sourceDownloadUrl": "https://firebasestorage.googleapis.com/v0/b/uevrprofiles.appspot.com/o/profiles%2f4be37cad-5a37-423c-95e7-349bbbbab92a.zip?alt=media",
  "description": "Native Stereo.",
  "downloadDate": "2026-03-13T01:14:15Z",
  "zipHash": "CB6814389CEDDC23231B5841DA7B5665",
  "downloadUrl": "https://gitfolderdownloader.github.io/?url=https%3A%2F%2Fgithub.com%2Fuevr-profiles%2Frepo%2Ftree%2Fmain%2Fprofiles%2F4be37cad-5a37-423c-95e7-349bbbbab92a&name=DeliverUsMars"
}
