{
  "ID": "333fa26d-62c7-483f-9a0e-b67341d69abc",
  "exeName": "Game00-Win64-Shipping",
  "gameName": "Machine Tower 2984",
  "authorName": "KingEJ",
  "modifiedDate": "2026-02-08T23:00:00Z",
  "createdDate": "2026-02-08T23:00:00Z",
  "downloadDate": "2026-03-14T02:36:10Z",
  "sourceName": "uevr-profiles.com",
  "sourceUrl": "https://uevr-profiles.com/game/333fa26d-62c7-483f-9a0e-b67341d69abc",
  "zipHash": "1A8779BC9139F1B87BA8722B1EECB34A",
  "downloadUrl": "https://gitfolderdownloader.github.io/?url=https%3a%2f%2fgithub.com%2fuevr-profiles%2frepo%2ftree%2fmain%2fprofiles%2f333fa26d-62c7-483f-9a0e-b67341d69abc&name=Game00-Win64-Shipping",
  "sourceDownloadUrl": "https://firebasestorage.googleapis.com/v0/b/uevrprofiles.appspot.com/o/profiles%2FGame00-Win64-Shipping.zip?alt=media",
  "description": "1st person profile 1st\\3rd DpadR  Note: Disable on loading or the next area will crash.",
  "tags": [
    "3DOF"
  ]
}
