{
  "ID": "3e1b8a0d-77db-4313-b8d4-507ee1348f4a",
  "exeName": "JediSurvivor",
  "gameName": "STAR WARS Jedi: Survivor™",
  "authorName": "oneup03",
  "modifiedDate": "2024-11-27T23:00:00Z",
  "createdDate": "2024-11-27T23:00:00Z",
  "downloadDate": "2026-03-14T02:36:13Z",
  "sourceName": "uevr-profiles.com",
  "sourceUrl": "https://uevr-profiles.com/game/3e1b8a0d-77db-4313-b8d4-507ee1348f4a",
  "zipHash": "FFAB26B99A954DFCC9ABED0D07228EF6",
  "downloadUrl": "https://gitfolderdownloader.github.io/?url=https%3a%2f%2fgithub.com%2fuevr-profiles%2frepo%2ftree%2fmain%2fprofiles%2f3e1b8a0d-77db-4313-b8d4-507ee1348f4a&name=JediSurvivor_2",
  "sourceDownloadUrl": "https://firebasestorage.googleapis.com/v0/b/uevrprofiles.appspot.com/o/profiles%2FJediSurvivor_2.zip?alt=media",
  "description": "Things I added: Disabled Occlusion Queries as they caused bad flickering of objects in opposite e..."
}
